keum/__init__.py
keum/babyjubjub.py
keum/bn254.py
keum/ec.py
keum/ff.py
keum/grumpkin.py
keum/pallas.py
keum/permutation.py
keum/secp256k1.py
keum/secp256r1.py
keum/tweedledee.py
keum/tweedledum.py
keum/vesta.py
keum-0.2.0.dist-info/LICENSE
keum-0.2.0.dist-info/METADATA
keum-0.2.0.dist-info/WHEEL
keum-0.2.0.dist-info/RECORD
