Metadata-Version: 2.1
Name: keum
Version: 0.2.0
Summary: Modular elliptic curve library implementation in Python for experimentations
Author: Danny Willems
Author-email: danny@badass.be
Requires-Python: >=3.11,<4.0
Classifier: License :: OSI Approved :: MIT License
Classifier: Operating System :: OS Independent
Classifier: Programming Language :: Python :: 3
Classifier: Programming Language :: Python :: 3.11
Requires-Dist: sympy
